callcounter/__init__.py
callcounter/middleware.py
callcounter-0.1.0.dist-info/LICENSE
callcounter-0.1.0.dist-info/METADATA
callcounter-0.1.0.dist-info/WHEEL
callcounter-0.1.0.dist-info/top_level.txt
callcounter-0.1.0.dist-info/RECORD
